{
    "openIdConfig": {
        "authorization_endpoint": null,
        "token_endpoint_auth_methods_supported": [],
        "token_endpoint": null,
        "scopes_supported": [
            "AIS",
            "PIS"
        ],
        "scopes": {
            "AIS": "openid read_accounts_list read_accounts",
            "PIS": "openid instant_sepa_credit_transfers"
        },
        "id_token_signing_alg_values_supported": [
            "PS256"
        ],
        "request_object_signing_alg_values_supported": [
            "PS256"
        ],
        "grant_types_supported": []
    },
    "psd2Config": {
        "consentApiUri": "https://api-sandbox.unicredit.bg/hydrogen/v1/consents",
        "accountsApiUri": "https://api-sandbox.unicredit.bg/hydrogen/v1/accounts",
        "paymentInitiationApiUri": "https://api-sandbox.unicredit.bg/hydrogen/v1/{payment-service}/{payment-product}",
        "paymentApiUri": "https://api-sandbox.unicredit.bg/hydrogen/v1/{payment-service}/{payment-product}/{paymentId}",
        "paymentStatusApiUri": "https://api-sandbox.unicredit.bg/hydrogen/v1/{payment-service}/{payment-product}/{paymentId}/status",
        "consentStatusApiUri": "https://api-sandbox.unicredit.bg/hydrogen/v1/consents/{consentId}/status"
    },
    "id": "unicredit-bg-sandbox",
    "aspspId": "unicredit-bg",
    "identity": {
        "memberState": "BG",
        "developerPortalUri": "https://developer.unicredit.eu/",
        "openIDConfigEndPointUri": "",
        "customerFriendlyDescription": "",
        "customerFriendlyLogoUri": "assets/img/banks/unicredit-bg.svg",
        "organisationCommonName": "UniCredit Bulbank",
        "termsOfService": "",
        "customerFriendlyName": "UniCredit Bulbank (sandbox)",
        "name": "UniCredit Bulbank",
        "website": "https://www.unicreditbulbank.bg/",
        "countries": [
            "BG"
        ],
        "weight": 0
    },
    "roles": [
        "aisp",
        "pisp",
        "cbpii"
    ]
}